<?xml version="1.0" encoding="UTF-8" standalone="no" ?>
	<ROOT xmlns:xsi="http://www.w3.org/2001/XMLSchema-instance" xsi:noNamespaceSchemaLocation="ConfigurationInfo.xsd">
		<CONFIGURATION Name="FEConfiguration">
			<VIEW Name="FE_CONFIGURATION" Type="File,Database,DatabaseTest" Description="Test%0A%0A%0Athis.">
				<COLUMN Type="Data" 	 Name="SupervisorType" 	 StorageName="SUPERVISOR_TYPE" 		DataType="VARCHAR2" 		DataChoices=""/>
				<COLUMN Type="MultilineData" 	 Name="SupervisorInstance" 	 StorageName="SUPERVISOR_INSTANCE" 		DataType="VARCHAR2" 		DataChoices=""/>
				<COLUMN Type="UID" 	 Name="FrontEndId" 	 StorageName="FRONT_END_ID" 		DataType="VARCHAR2" 		DataChoices=""/>
				<COLUMN Type="FixedChoiceData" 	 Name="FrontEndType" 	 StorageName="FRONT_END_TYPE" 		DataType="VARCHAR2" 		DataChoices="Type1,Type2,New%20Type%204"/>
				<COLUMN Type="BitMap" 	 Name="PixelMask" 	 StorageName="PIXEL_MASK" 		DataType="VARCHAR2" 		DataChoices="2,100,4,DEFAULT,DEFAULT,DEFAULT,100%3A150,DEFAULT,DEFAULT,DEFAULT,DEFAULT,DEFAULT,No,Yes,No,No"/>
				<COLUMN Type="Comment" 	 Name="CommentDescription" 	 StorageName="COMMENT_DESCRIPTION" 		DataType="VARCHAR2" 		DataChoices=""/>
				<COLUMN Type="Author" 	 Name="Author" 	 StorageName="AUTHOR" 		DataType="VARCHAR2" 		DataChoices=""/>
				<COLUMN Type="Timestamp" 	 Name="RecordInsertionTime" 	 StorageName="RECORD_INSERTION_TIME" 		DataType="TIMESTAMP WITH TIMEZONE" 		DataChoices=""/>
			</VIEW>
		</CONFIGURATION>
	</ROOT>
